00_spec/ref/Code/Quick-sort-algorithm/partition.v
module partition(xin, xout, i, j, loc_in, loc_out, clk, init, complete, read, write);
  parameter N = 8;
  input clk, init, read, write;
  input [31:0] xin;
  input [31:0] i, j;
  input [31:0] loc_in;
  output reg [31:0] loc_out, xout;
  output reg complete;
  reg [31:0] vec[0:N-1];
  reg [31:0] right, left, loc;
  reg set;
  reg [31:0] temp, count;
  reg [3:0] state;
  parameter S0=4'b0000, S1=4'b0001, S2=4'b0010, S3=4'b0011, S4=4'b0100,
            S5=4'b0101, S6=4'b0110, S7=4'b0111, S8=4'b1000;

  always @(posedge clk) begin
    // Read and write operations
    if (read && count != N) begin
      vec[count] <= xin;
      count <= count + 1;
    end
    else if (write && count != N) begin
      xout <= vec[count];
      count <= count + 1;
    end
    else if (~read && ~write) begin
      count <= 0;
    end

    // State machine
    case (state)
      S0: begin
        state <= init ? S1 : S0;
        complete <= 0;
        loc <= loc_in;
        left <= i;
        right <= j;
      end
      S1: begin
        complete <= 0;
        if (vec[loc] <= vec[right] && loc != right)
          state <= S2;
        else if (vec[loc] > vec[right]) begin
          state <= S4;
          // Swap vec[loc] and vec[right]
          temp <= vec[loc];
          vec[loc] <= vec[right];
          vec[right] <= temp;
          loc <= right;
        end
        else if (loc == right)
          state <= S3;
      end
      S2: begin
        if (vec[loc] <= vec[right] && loc != right) begin
          state <= S2;
          right <= right - 1;
        end
        else if (vec[loc] > vec[right]) begin
          state <= S4;
          // Swap vec[loc] and vec[right]
          temp <= vec[loc];
          vec[loc] <= vec[right];
          vec[right] <= temp;
          loc <= right;
        end
        else if (loc == right)
          state <= S3;
      end
      S3: begin
        state <= S0;
        set <= 1;
        complete <= 1;
        loc_out <= loc;
      end
      S4: begin
        if (vec[loc] >= vec[left] && left != loc)
          state <= S5;
        else if (vec[loc] < vec[left]) begin
          state <= S7;
          // Swap vec[loc] and vec[left]
          temp <= vec[loc];
          vec[loc] <= vec[left];
          vec[left] <= temp;
          loc <= left;
        end
        else if (loc == left)
          state <= S6;
      end
      S5: begin
        if (vec[loc] >= vec[left] && left != loc) begin
          state <= S5;
          left <= left + 1;
        end
        else if (vec[loc] < vec[left]) begin
          state <= S7;
          // Swap vec[loc] and vec[left]
          temp <= vec[loc];
          vec[loc] <= vec[left];
          vec[left] <= temp;
          loc <= left;
        end
        else if (loc == left)
          state <= S6;
      end
      S6: begin
        state <= init ? S0 : S6;
        set <= 1;
        complete <= 1;
        loc_out <= loc;
      end
      S7: begin
        state <= S1;
      end
      default: state <= S0; // Added for robustness
    endcase
  end
endmodule

00_spec/ref/Code/Quick-sort-algorithm/stack.v
module stack(clk,val1,val2,push,pop,ret1,ret2,empty);
  parameter N = 64;
  input[31:0] val1,val2;
  input clk,push,pop;
  output reg empty;
  output reg[31:0] ret1,ret2;
  reg[31:0]  counter;
  reg[31:0] mem[0:N];
  always @(posedge clk)
  begin
    if(push)
    begin
      mem[counter]<=val2;
      mem[counter+1]<=val1;
      counter<=counter+2;
    end
    else if(pop && counter!=0)
    begin
      ret1<=mem[counter-1];
      ret2<=mem[counter-2];
      counter<=counter-2;
    end
  end
  always @(counter)
  begin
    empty<=(counter==0);
  end
endmodule

00_spec/ref/Code/Quick-sort-algorithm/controller.v
module controller(clk,init,size,empty,complete,ret1,ret2,val1,val2,loc,push,pop,init_p,Qcomp);
  input clk,init,empty,complete;
  input[31:0] ret1,ret2,loc,size;
  output reg push,pop,init_p;
  output reg[31:0] val1,val2;
  output reg Qcomp;
  parameter S0=4'b0000,S1=4'b0001,S2=4'b0010,S3=4'b0011,S4=4'b0100,S5=4'b0101,S6=4'b0110,S7=4'b0111,S8=4'b1000,S9=4'b1001,Si=4'b1010;
  reg[3:0] state;
  reg[31:0]  i,j;
  //reg[31:0] loc;
  always @(posedge clk)
  begin
    case(state)
      S0:
        state<=init?S9:Si;
      Si:
        state<=init?S0:Si;
      S9:
        state<=S1;
      S1:
        state<=empty?S0:S2;
      S2:
        state<=S3;
      S3:
        state<=S4;
      S4:
        state<=complete?S5:S4;
      S5:
        state<=S6;
      S6:
        state<=S7;
      S7:
        state<=S8;
      S8:
        state<=S1;
    endcase
  end
  always @(state)
  begin
    case(state)
      S0:
      begin
        push<=1;
        val1<=0;
        val2<=size-1;
        Qcomp<=0;
        init_p<=0;
      end
      Si:
      begin
        Qcomp<=1;
        push<=0;
      end
      S9:
      begin
        push<=0;
      end
      S2:
      begin
        pop<=1;
        push<=0;
      end
      S3:
        pop<=0;
      S4:
        init_p<=1;
      S5:
        init_p<=0;
      S6:
      begin
        if(ret1<(loc-1) && loc>0)
        begin
          push<=1;
          val1<=ret1;
          val2<=loc-1;
        end
      end
      S7:
      begin
        if((loc+1)<ret2 && loc[31]==0)
        begin
          push<=1;
          val1<=loc+1;
          val2<=ret2;
        end
      end
      S8:
        push<=0;
    endcase
  end
endmodule

00_spec/ref/Code/Quick-sort-algorithm/QSort.v
module  QSort(xin,xout,init,clk,Qcomp,read,write);
  parameter N=8 ;
  input clk,init,read,write;
  output Qcomp;
  input[31:0] xin;
  output[31:0] xout;
  wire[31:0] ret1,ret2,val1,val2,out;
  wire[31:0] size;
  wire init_p,empty,complete,push,pop,c;
  assign size=N;
  assign c=clk;
  controller C(clk,init,size,empty,complete,ret1,ret2,val1,val2,out,push,pop,init_p,Qcomp);
  stack S(clk,val1,val2,push,pop,ret1,ret2,empty);
  partition P(xin,xout,ret1,ret2,ret1,out,clk,init_p,complete,read,write);
endmodule

00_spec/ref/Code/Quick-sort-algorithm/Qtest.v
module Qtest;
  parameter N = 8;
  reg clk, init, read, write;
  reg [31:0] xin;
  wire [31:0] xout;
  wire Qcomp;
  integer i, c;
  integer file, scan_result;
  reg [31:0] temp;

  QSort DUT(xin, xout, init, clk, Qcomp, read, write);

  initial begin
    // Initialize signals and DUT
    clk = 0;
    init = 0;
    read = 0;
    write = 0;
    DUT.P.state = 4'b0000;
    DUT.C.state = 4'b0000;
    DUT.P.set = 0;
    DUT.S.counter = 0;
    for (i = 0; i < 64; i = i + 1) begin
      DUT.S.mem[i] = 0;
    end

    // Open unsort.txt and read numbers
    #10;
    file = $fopen("unsort.txt", "r");
    if (file == 0) begin
      $display("Error: Could not open unsort.txt");
      $finish;
    end
    read = 1;
    for (i = 0; i < N; i = i + 1) begin
      scan_result = $fscanf(file, "%d\n", temp);
      if (scan_result != 1) begin
        $display("Error: Failed to read number %0d from unsort.txt", i);
        $fclose(file);
        $finish;
      end
      xin = temp;
      $display("Time %0t: Loading vec[%0d] = %0d", $time, i, xin);
      #10;
    end
    $fclose(file);
    read = 0;

    // Display initial array
    for (c = 0; c < N; c = c + 1) begin
      $write("%0d ", DUT.P.vec[c]);
    end
    $write("\n");

    // Trigger sorting
    #10 init = 1;
    #20 init = 0;

    // Wait for completion with timeout
    fork
      wait (Qcomp);
      #10000 begin
        $display("Error: Simulation timed out waiting for Qcomp");
        $finish;
      end
    join_any
    #10 write = 1;
    #80 write = 0;
    #10 $finish;
  end

  // Clock generation
  always #5 clk = ~clk;

  // Waveform dumping
  initial begin
    $dumpfile("Qtest.vcd");
    $dumpvars(0, Qtest);
  end

  // Display sorted array on Qcomp
  always @(posedge Qcomp) begin
    $display("Time %0t: Sorting complete, Qcomp = 1", $time);
    for (c = 0; c < N; c = c + 1) begin
      $write("%0d ", DUT.P.vec[c]);
    end
    $write("\n");
  end

endmodule
// module Qtest;
// parameter N=8 ;
// reg clk,init,read,write;
// reg[31:0] xin;
// wire[31:0] xout;
// wire Qcomp;
// integer i,c;
// integer seed=10;
// QSort DUT(xin,xout,init,clk,Qcomp,read,write);
// initial begin
//     clk=0;
//     init=0;
//     read=0;
//     write=0;
//     DUT.P.state=4'b0000;
//     DUT.C.state=4'b0000;
//     DUT.P.set=0;
//    // DUT.P.vec[0]=13;DUT.P.vec[1]=2;DUT.P.vec[2]=8;DUT.P.vec[3]=12;DUT.P.vec[4]=1;DUT.P.vec[5]=3;DUT.P.vec[6]=31;DUT.P.vec[7]=22;
//     DUT.S.counter=0;
//     for(i=0;i<64;i=i+1)begin
//       DUT.S.mem[i]=0;
//     end
//     #10 read=1;
//     xin=$urandom(seed)%100;
//     for(i=0;i<7;i=i+1)begin
//       #10 xin=$urandom(seed)%100;
//     end
//     //xin=6;#10 xin=2;#10 xin=8;#10 xin=12;#10 xin=1;#10 xin=3;#10 xin=31;#10 xin=22;
//     #10 read=0;
//     for(c=0;c<N;c=c+1)begin
//       $write("%0d ",DUT.P.vec[c]);
//     end
//     $write("\n");
//     #10 init=1;
//     #20 init=0;
//     #1000 write=1;
//     #5000 $finish;
// end
// always #5 clk=~clk;
// initial begin
//     $dumpfile("Qtest.vcd");
//     $dumpvars(0,Qtest);
// end
// always @(posedge Qcomp) begin
//     for(c=0;c<N;c=c+1)begin
//       $write("%0d ",DUT.P.vec[c]);
//     end
//     $write("\n");
// end
// endmodule

00_spec/ref/Code/Quick-sort-algorithm/Qtest.vcd
$version Generated by VerilatedVcd $end
$timescale 1ps $end
 $scope module TOP $end
  $scope module Qtest $end
   $var wire 32 J N [31:0] $end
   $var wire 1 B clk $end
   $var wire 1 # init $end
   $var wire 1 $ read $end
   $var wire 1 % write $end
   $var wire 32 & xin [31:0] $end
   $var wire 32 0 xout [31:0] $end
   $var wire 1 + Qcomp $end
   $var wire 32 ' i [31:0] $end
   $var wire 32 C c [31:0] $end
   $var wire 32 ( file [31:0] $end
   $var wire 32 ) scan_result [31:0] $end
   $var wire 32 * temp [31:0] $end
   $scope module DUT $end
    $var wire 32 J N [31:0] $end
    $var wire 1 B clk $end
    $var wire 1 # init $end
    $var wire 1 $ read $end
    $var wire 1 % write $end
    $var wire 1 + Qcomp $end
    $var wire 32 & xin [31:0] $end
    $var wire 32 0 xout [31:0] $end
    $var wire 32 1 ret1 [31:0] $end
    $var wire 32 2 ret2 [31:0] $end
    $var wire 32 , val1 [31:0] $end
    $var wire 32 - val2 [31:0] $end
    $var wire 32 3 out [31:0] $end
    $var wire 32 J size [31:0] $end
    $var wire 1 D init_p $end
    $var wire 1 E empty $end
    $var wire 1 4 complete $end
    $var wire 1 . push $end
    $var wire 1 / pop $end
    $var wire 1 B c $end
    $scope module C $end
     $var wire 1 B clk $end
     $var wire 1 # init $end
     $var wire 1 E empty $end
     $var wire 1 4 complete $end
     $var wire 32 1 ret1 [31:0] $end
     $var wire 32 2 ret2 [31:0] $end
     $var wire 32 3 loc [31:0] $end
     $var wire 32 J size [31:0] $end
     $var wire 1 . push $end
     $var wire 1 / pop $end
     $var wire 1 D init_p $end
     $var wire 32 , val1 [31:0] $end
     $var wire 32 - val2 [31:0] $end
     $var wire 1 + Qcomp $end
     $var wire 4 K S0 [3:0] $end
     $var wire 4 L S1 [3:0] $end
     $var wire 4 M S2 [3:0] $end
     $var wire 4 N S3 [3:0] $end
     $var wire 4 O S4 [3:0] $end
     $var wire 4 P S5 [3:0] $end
     $var wire 4 Q S6 [3:0] $end
     $var wire 4 R S7 [3:0] $end
     $var wire 4 S S8 [3:0] $end
     $var wire 4 T S9 [3:0] $end
     $var wire 4 U Si [3:0] $end
     $var wire 4 F state [3:0] $end
     $var wire 32 V i [31:0] $end
     $var wire 32 W j [31:0] $end
    $upscope $end
    $scope module P $end
     $var wire 32 J N [31:0] $end
     $var wire 1 B clk $end
     $var wire 1 D init $end
     $var wire 1 $ read $end
     $var wire 1 % write $end
     $var wire 32 & xin [31:0] $end
     $var wire 32 1 i [31:0] $end
     $var wire 32 2 j [31:0] $end
     $var wire 32 1 loc_in [31:0] $end
     $var wire 32 3 loc_out [31:0] $end
     $var wire 32 0 xout [31:0] $end
     $var wire 1 4 complete $end
     $var wire 32 5 vec[0] [31:0] $end
     $var wire 32 6 vec[1] [31:0] $end
     $var wire 32 7 vec[2] [31:0] $end
     $var wire 32 8 vec[3] [31:0] $end
     $var wire 32 9 vec[4] [31:0] $end
     $var wire 32 : vec[5] [31:0] $end
     $var wire 32 ; vec[6] [31:0] $end
     $var wire 32 < vec[7] [31:0] $end
     $var wire 32 = right [31:0] $end
     $var wire 32 > left [31:0] $end
     $var wire 32 ? loc [31:0] $end
     $var wire 1 G set $end
     $var wire 32 @ temp [31:0] $end
     $var wire 32 A count [31:0] $end
     $var wire 4 H state [3:0] $end
     $var wire 4 K S0 [3:0] $end
     $var wire 4 L S1 [3:0] $end
     $var wire 4 M S2 [3:0] $end
     $var wire 4 N S3 [3:0] $end
     $var wire 4 O S4 [3:0] $end
     $var wire 4 P S5 [3:0] $end
     $var wire 4 Q S6 [3:0] $end
     $var wire 4 R S7 [3:0] $end
     $var wire 4 S S8 [3:0] $end
    $upscope $end
    $scope module S $end
     $var wire 32 X N [31:0] $end
     $var wire 32 , val1 [31:0] $end
     $var wire 32 - val2 [31:0] $end
     $var wire 1 B clk $end
     $var wire 1 . push $end
     $var wire 1 / pop $end
     $var wire 1 E empty $end
     $var wire 32 1 ret1 [31:0] $end
     $var wire 32 2 ret2 [31:0] $end
     $var wire 32 I counter [31:0] $end
    $upscope $end
   $upscope $end
  $upscope $end
 $upscope $end
$enddefinitions $end


#0
0#
0$
0%
b00000000000000000000000000000000 &
b00000000000000000000000001000000 '
b00000000000000000000000000000000 (
b00000000000000000000000000000000 )
b00000000000000000000000000000000 *
0+
b00000000000000000000000000000000 ,
b00000000000000000000000000000111 -
1.
0/
b00000000000000000000000000000000 0
b00000000000000000000000000000000 1
b00000000000000000000000000000000 2
b00000000000000000000000000000000 3
04
b00000000000000000000000000000000 5
b00000000000000000000000000000000 6
b00000000000000000000000000000000 7
b00000000000000000000000000000000 8
b00000000000000000000000000000000 9
b00000000000000000000000000000000 :
b00000000000000000000000000000000 ;
b00000000000000000000000000000000 <
b00000000000000000000000000000000 =
b00000000000000000000000000000000 >
b00000000000000000000000000000000 ?
b00000000000000000000000000000000 @
b00000000000000000000000000000000 A
0B
b00000000000000000000000000000000 C
0D
1E
b0000 F
0G
b0000 H
b00000000000000000000000000000000 I
b00000000000000000000000000001000 J
b0000 K
b0001 L
b0010 M
b0011 N
b0100 O
b0101 P
b0110 Q
b0111 R
b1000 S
b1001 T
b1010 U
b00000000000000000000000000000000 V
b00000000000000000000000000000000 W
b00000000000000000000000001000000 X
#5
1+
0.
1B
b00000000000000000000000000001000 C
0E
b1010 F
b00000000000000000000000000000010 I
#10
1$
b00000000000000000000000001001001 &
b10000000000000000000000000101100 (
b00000000000000000000000000000001 )
b00000000000000000000000001001001 *
0B
#15
b00000000000000000000000001001001 5
b00000000000000000000000000000001 A
1B
#20
b00000000000000000000000000000100 &
b00000000000000000000000000000001 '
b00000000000000000000000000000100 *
0B
#25
b00000000000000000000000000000100 6
b00000000000000000000000000000010 A
1B
#30
b00000000000000000000000000110110 &
b00000000000000000000000000000010 '
b00000000000000000000000000110110 *
0B
#35
b00000000000000000000000000110110 7
b00000000000000000000000000000011 A
1B
#40
b00000000000000000000000000111101 &
b00000000000000000000000000000011 '
b00000000000000000000000000111101 *
0B
#45
b00000000000000000000000000111101 8
b00000000000000000000000000000100 A
1B
#50
b00000000000000000000000001001001 &
b00000000000000000000000000000100 '
b00000000000000000000000001001001 *
0B
#55
b00000000000000000000000001001001 9
b00000000000000000000000000000101 A
1B
#60
b00000000000000000000000000000001 &
b00000000000000000000000000000101 '
b00000000000000000000000000000001 *
0B
#65
b00000000000000000000000000000001 :
b00000000000000000000000000000110 A
1B
#70
b00000000000000000000000000011010 &
b00000000000000000000000000000110 '
b00000000000000000000000000011010 *
0B
#75
b00000000000000000000000000011010 ;
b00000000000000000000000000000111 A
1B
#80
b00000000000000000000000000111011 &
b00000000000000000000000000000111 '
b00000000000000000000000000111011 *
0B
#85
b00000000000000000000000000111011 <
b00000000000000000000000000001000 A
1B
#90
0$
b00000000000000000000000000001000 '
0B
#95
b00000000000000000000000000000000 A
1B
#100
1#
0B
#105
0+
1.
1B
b0000 F
#110
0B
#115
0.
1B
b1001 F
b00000000000000000000000000000100 I
#120
0#
0B
#125
1B
b0001 F
#130
0B
#135
1/
1B
b0010 F
#140
0B
#145
0/
b00000000000000000000000000000111 2
1B
b0011 F
b00000000000000000000000000000010 I
#150
0B
#155
b00000000000000000000000000000111 =
1B
1D
b0100 F
#160
0B
#165
1B
b0001 H
#170
0B
#175
b00000000000000000000000000111011 5
b00000000000000000000000000000000 <
b00000000000000000000000000000111 ?
b00000000000000000000000001001001 @
1B
b0100 H
#180
0B
#185
b00000000000000000000000001001001 5
b00000000000000000000000000111011 <
b00000000000000000000000000000000 ?
b00000000000000000000000000000000 @
1B
b0111 H
#190
0B
#195
1B
b0001 H
#200
0B
#205
b00000000000000000000000000111011 5
b00000000000000000000000000000000 <
b00000000000000000000000000000111 ?
b00000000000000000000000001001001 @
1B
b0100 H
#210
0B
#215
b00000000000000000000000001001001 5
b00000000000000000000000000111011 <
b00000000000000000000000000000000 ?
b00000000000000000000000000000000 @
1B
b0111 H
#220
0B
#225
1B
b0001 H
#230
0B
#235
b00000000000000000000000000111011 5
b00000000000000000000000000000000 <
b00000000000000000000000000000111 ?
b00000000000000000000000001001001 @
1B
b0100 H
#240
0B
#245
b00000000000000000000000001001001 5
b00000000000000000000000000111011 <
b00000000000000000000000000000000 ?
b00000000000000000000000000000000 @
1B
b0111 H
#250
0B
#255
1B
b0001 H
#260
0B
#265
b00000000000000000000000000111011 5
b00000000000000000000000000000000 <
b00000000000000000000000000000111 ?
b00000000000000000000000001001001 @
1B
b0100 H
#270
0B
#275
b00000000000000000000000001001001 5
b00000000000000000000000000111011 <
b00000000000000000000000000000000 ?
b00000000000000000000000000000000 @
1B
b0111 H
#280
0B
#285
1B
b0001 H
#290
0B
#295
b00000000000000000000000000111011 5
b00000000000000000000000000000000 <
b00000000000000000000000000000111 ?
b00000000000000000000000001001001 @
1B
b0100 H
#300
0B
#305
b00000000000000000000000001001001 5
b00000000000000000000000000111011 <
b00000000000000000000000000000000 ?
b00000000000000000000000000000000 @
1B
b0111 H
#310
0B
#315
1B
b0001 H
#320
0B
#325
b00000000000000000000000000111011 5
b00000000000000000000000000000000 <
b00000000000000000000000000000111 ?
b00000000000000000000000001001001 @
1B
b0100 H
#330
0B
#335
b00000000000000000000000001001001 5
b00000000000000000000000000111011 <
b00000000000000000000000000000000 ?
b00000000000000000000000000000000 @
1B
b0111 H
#340
0B
#345
1B
b0001 H
#350
0B
#355
b00000000000000000000000000111011 5
b00000000000000000000000000000000 <
b00000000000000000000000000000111 ?
b00000000000000000000000001001001 @
1B
b0100 H
#360
0B
#365
b00000000000000000000000001001001 5
b00000000000000000000000000111011 <
b00000000000000000000000000000000 ?
b00000000000000000000000000000000 @
1B
b0111 H
#370
0B
#375
1B
b0001 H
#380
0B
#385
b00000000000000000000000000111011 5
b00000000000000000000000000000000 <
b00000000000000000000000000000111 ?
b00000000000000000000000001001001 @
1B
b0100 H
#390
0B
#395
b00000000000000000000000001001001 5
b00000000000000000000000000111011 <
b00000000000000000000000000000000 ?
b00000000000000000000000000000000 @
1B
b0111 H
#400
0B
#405
1B
b0001 H
#410
0B
#415
b00000000000000000000000000111011 5
b00000000000000000000000000000000 <
b00000000000000000000000000000111 ?
b00000000000000000000000001001001 @
1B
b0100 H
#420
0B
#425
b00000000000000000000000001001001 5
b00000000000000000000000000111011 <
b00000000000000000000000000000000 ?
b00000000000000000000000000000000 @
1B
b0111 H
#430
0B
#435
1B
b0001 H
#440
0B
#445
b00000000000000000000000000111011 5
b00000000000000000000000000000000 <
b00000000000000000000000000000111 ?
b00000000000000000000000001001001 @
1B
b0100 H
#450
0B
#455
b00000000000000000000000001001001 5
b00000000000000000000000000111011 <
b00000000000000000000000000000000 ?
b00000000000000000000000000000000 @
1B
b0111 H
#460
0B
#465
1B
b0001 H
#470
0B
#475
b00000000000000000000000000111011 5
b00000000000000000000000000000000 <
b00000000000000000000000000000111 ?
b00000000000000000000000001001001 @
1B
b0100 H
#480
0B
#485
b00000000000000000000000001001001 5
b00000000000000000000000000111011 <
b00000000000000000000000000000000 ?
b00000000000000000000000000000000 @
1B
b0111 H
#490
0B
#495
1B
b0001 H
#500
0B
#505
b00000000000000000000000000111011 5
b00000000000000000000000000000000 <
b00000000000000000000000000000111 ?
b00000000000000000000000001001001 @
1B
b0100 H
#510
0B
#515
b00000000000000000000000001001001 5
b00000000000000000000000000111011 <
b00000000000000000000000000000000 ?
b00000000000000000000000000000000 @
1B
b0111 H
#520
0B
#525
1B
b0001 H
#530
0B
#535
b00000000000000000000000000111011 5
b00000000000000000000000000000000 <
b00000000000000000000000000000111 ?
b00000000000000000000000001001001 @
1B
b0100 H
#540
0B
#545
b00000000000000000000000001001001 5
b00000000000000000000000000111011 <
b00000000000000000000000000000000 ?
b00000000000000000000000000000000 @
1B
b0111 H
#550
0B
#555
1B
b0001 H
#560
0B
#565
b00000000000000000000000000111011 5
b00000000000000000000000000000000 <
b00000000000000000000000000000111 ?
b00000000000000000000000001001001 @
1B
b0100 H
#570
0B
#575
b00000000000000000000000001001001 5
b00000000000000000000000000111011 <
b00000000000000000000000000000000 ?
b00000000000000000000000000000000 @
1B
b0111 H
#580
0B
#585
1B
b0001 H
#590
0B
#595
b00000000000000000000000000111011 5
b00000000000000000000000000000000 <
b00000000000000000000000000000111 ?
b00000000000000000000000001001001 @
1B
b0100 H
#600
0B
#605
b00000000000000000000000001001001 5
b00000000000000000000000000111011 <
b00000000000000000000000000000000 ?
b00000000000000000000000000000000 @
1B
b0111 H
#610
0B
#615
1B
b0001 H
#620
0B
#625
b00000000000000000000000000111011 5
b00000000000000000000000000000000 <
b00000000000000000000000000000111 ?
b00000000000000000000000001001001 @
1B
b0100 H
#630
0B
#635
b00000000000000000000000001001001 5
b00000000000000000000000000111011 <
b00000000000000000000000000000000 ?
b00000000000000000000000000000000 @
1B
b0111 H
#640
0B
#645
1B
b0001 H
#650
0B
#655
b00000000000000000000000000111011 5
b00000000000000000000000000000000 <
b00000000000000000000000000000111 ?
b00000000000000000000000001001001 @
1B
b0100 H
#660
0B
#665
b00000000000000000000000001001001 5
b00000000000000000000000000111011 <
b00000000000000000000000000000000 ?
b00000000000000000000000000000000 @
1B
b0111 H
#670
0B
#675
1B
b0001 H
#680
0B
#685
b00000000000000000000000000111011 5
b00000000000000000000000000000000 <
b00000000000000000000000000000111 ?
b00000000000000000000000001001001 @
1B
b0100 H
#690
0B
#695
b00000000000000000000000001001001 5
b00000000000000000000000000111011 <
b00000000000000000000000000000000 ?
b00000000000000000000000000000000 @
1B
b0111 H
#700
0B
#705
1B
b0001 H
#710
0B
#715
b00000000000000000000000000111011 5
b00000000000000000000000000000000 <
b00000000000000000000000000000111 ?
b00000000000000000000000001001001 @
1B
b0100 H
#720
0B
#725
b00000000000000000000000001001001 5
b00000000000000000000000000111011 <
b00000000000000000000000000000000 ?
b00000000000000000000000000000000 @
1B
b0111 H
#730
0B
#735
1B
b0001 H
#740
0B
#745
b00000000000000000000000000111011 5
b00000000000000000000000000000000 <
b00000000000000000000000000000111 ?
b00000000000000000000000001001001 @
1B
b0100 H
#750
0B
#755
b00000000000000000000000001001001 5
b00000000000000000000000000111011 <
b00000000000000000000000000000000 ?
b00000000000000000000000000000000 @
1B
b0111 H
#760
0B
#765
1B
b0001 H
#770
0B
#775
b00000000000000000000000000111011 5
b00000000000000000000000000000000 <
b00000000000000000000000000000111 ?
b00000000000000000000000001001001 @
1B
b0100 H
#780
0B
#785
b00000000000000000000000001001001 5
b00000000000000000000000000111011 <
b00000000000000000000000000000000 ?
b00000000000000000000000000000000 @
1B
b0111 H
#790
0B
#795
1B
b0001 H
#800
0B
#805
b00000000000000000000000000111011 5
b00000000000000000000000000000000 <
b00000000000000000000000000000111 ?
b00000000000000000000000001001001 @
1B
b0100 H
#810
0B
#815
b00000000000000000000000001001001 5
b00000000000000000000000000111011 <
b00000000000000000000000000000000 ?
b00000000000000000000000000000000 @
1B
b0111 H
#820
0B
#825
1B
b0001 H
#830
0B
#835
b00000000000000000000000000111011 5
b00000000000000000000000000000000 <
b00000000000000000000000000000111 ?
b00000000000000000000000001001001 @
1B
b0100 H
#840
0B
#845
b00000000000000000000000001001001 5
b00000000000000000000000000111011 <
b00000000000000000000000000000000 ?
b00000000000000000000000000000000 @
1B
b0111 H
#850
0B
#855
1B
b0001 H
#860
0B
#865
b00000000000000000000000000111011 5
b00000000000000000000000000000000 <
b00000000000000000000000000000111 ?
b00000000000000000000000001001001 @
1B
b0100 H
#870
0B
#875
b00000000000000000000000001001001 5
b00000000000000000000000000111011 <
b00000000000000000000000000000000 ?
b00000000000000000000000000000000 @
1B
b0111 H
#880
0B
#885
1B
b0001 H
#890
0B
#895
b00000000000000000000000000111011 5
b00000000000000000000000000000000 <
b00000000000000000000000000000111 ?
b00000000000000000000000001001001 @
1B
b0100 H
#900
0B
#905
b00000000000000000000000001001001 5
b00000000000000000000000000111011 <
b00000000000000000000000000000000 ?
b00000000000000000000000000000000 @
1B
b0111 H
#910
0B
#915
1B
b0001 H
#920
0B
#925
b00000000000000000000000000111011 5
b00000000000000000000000000000000 <
b00000000000000000000000000000111 ?
b00000000000000000000000001001001 @
1B
b0100 H
#930
0B
#935
b00000000000000000000000001001001 5
b00000000000000000000000000111011 <
b00000000000000000000000000000000 ?
b00000000000000000000000000000000 @
1B
b0111 H
#940
0B
#945
1B
b0001 H
#950
0B
#955
b00000000000000000000000000111011 5
b00000000000000000000000000000000 <
b00000000000000000000000000000111 ?
b00000000000000000000000001001001 @
1B
b0100 H
#960
0B
#965
b00000000000000000000000001001001 5
b00000000000000000000000000111011 <
b00000000000000000000000000000000 ?
b00000000000000000000000000000000 @
1B
b0111 H
#970
0B
#975
1B
b0001 H
#980
0B
#985
b00000000000000000000000000111011 5
b00000000000000000000000000000000 <
b00000000000000000000000000000111 ?
b00000000000000000000000001001001 @
1B
b0100 H
#990
0B
#995
b00000000000000000000000001001001 5
b00000000000000000000000000111011 <
b00000000000000000000000000000000 ?
b00000000000000000000000000000000 @
1B
b0111 H
#1000
0B
#1005
1B
b0001 H
#1010
0B
#1015
b00000000000000000000000000111011 5
b00000000000000000000000000000000 <
b00000000000000000000000000000111 ?
b00000000000000000000000001001001 @
1B
b0100 H
#1020
0B
#1025
b00000000000000000000000001001001 5
b00000000000000000000000000111011 <
b00000000000000000000000000000000 ?
b00000000000000000000000000000000 @
1B
b0111 H
#1030
0B
#1035
1B
b0001 H
#1040
0B
#1045
b00000000000000000000000000111011 5
b00000000000000000000000000000000 <
b00000000000000000000000000000111 ?
b00000000000000000000000001001001 @
1B
b0100 H
#1050
0B
#1055
b00000000000000000000000001001001 5
b00000000000000000000000000111011 <
b00000000000000000000000000000000 ?
b00000000000000000000000000000000 @
1B
b0111 H
#1060
0B
#1065
1B
b0001 H
#1070
0B
#1075
b00000000000000000000000000111011 5
b00000000000000000000000000000000 <
b00000000000000000000000000000111 ?
b00000000000000000000000001001001 @
1B
b0100 H
#1080
0B
#1085
b00000000000000000000000001001001 5
b00000000000000000000000000111011 <
b00000000000000000000000000000000 ?
b00000000000000000000000000000000 @
1B
b0111 H
#1090
0B
#1095
1B
b0001 H
#1100
0B
#1105
b00000000000000000000000000111011 5
b00000000000000000000000000000000 <
b00000000000000000000000000000111 ?
b00000000000000000000000001001001 @
1B
b0100 H
#1110
0B
#1115
b00000000000000000000000001001001 5
b00000000000000000000000000111011 <
b00000000000000000000000000000000 ?
b00000000000000000000000000000000 @
1B
b0111 H
#1120
0B
#1125
1B
b0001 H
#1130
0B
#1135
b00000000000000000000000000111011 5
b00000000000000000000000000000000 <
b00000000000000000000000000000111 ?
b00000000000000000000000001001001 @
1B
b0100 H
#1140
0B
#1145
b00000000000000000000000001001001 5
b00000000000000000000000000111011 <
b00000000000000000000000000000000 ?
b00000000000000000000000000000000 @
1B
b0111 H
#1150
0B
#1155
1B
b0001 H
#1160
0B
#1165
b00000000000000000000000000111011 5
b00000000000000000000000000000000 <
b00000000000000000000000000000111 ?
b00000000000000000000000001001001 @
1B
b0100 H
#1170
0B
#1175
b00000000000000000000000001001001 5
b00000000000000000000000000111011 <
b00000000000000000000000000000000 ?
b00000000000000000000000000000000 @
1B
b0111 H
#1180
0B
#1185
1B
b0001 H
#1190
0B
#1195
b00000000000000000000000000111011 5
b00000000000000000000000000000000 <
b00000000000000000000000000000111 ?
b00000000000000000000000001001001 @
1B
b0100 H
#1200
0B
#1205
b00000000000000000000000001001001 5
b00000000000000000000000000111011 <
b00000000000000000000000000000000 ?
b00000000000000000000000000000000 @
1B
b0111 H
#1210
0B
#1215
1B
b0001 H
#1220
0B
#1225
b00000000000000000000000000111011 5
b00000000000000000000000000000000 <
b00000000000000000000000000000111 ?
b00000000000000000000000001001001 @
1B
b0100 H
#1230
0B
#1235
b00000000000000000000000001001001 5
b00000000000000000000000000111011 <
b00000000000000000000000000000000 ?
b00000000000000000000000000000000 @
1B
b0111 H
#1240
0B
#1245
1B
b0001 H
#1250
0B
#1255
b00000000000000000000000000111011 5
b00000000000000000000000000000000 <
b00000000000000000000000000000111 ?
b00000000000000000000000001001001 @
1B
b0100 H
#1260
0B
#1265
b00000000000000000000000001001001 5
b00000000000000000000000000111011 <
b00000000000000000000000000000000 ?
b00000000000000000000000000000000 @
1B
b0111 H
#1270
0B
#1275
1B
b0001 H
#1280
0B
#1285
b00000000000000000000000000111011 5
b00000000000000000000000000000000 <
b00000000000000000000000000000111 ?
b00000000000000000000000001001001 @
1B
b0100 H
#1290
0B
#1295
b00000000000000000000000001001001 5
b00000000000000000000000000111011 <
b00000000000000000000000000000000 ?
b00000000000000000000000000000000 @
1B
b0111 H
#1300
0B
#1305
1B
b0001 H
#1310
0B
