02_rtl/SS_detect_edge.sv
// i_pos_edge = 0 -> detect negedge edge
// i_pos_edge = 1 -> detect posedge edge
module SS_detect_edge(
    input logic                 i_clk       ,
    input logic                 i_rst_n     ,
    input logic                 i_pos_edge  ,
    input logic                 i_signal    ,
    output logic                o_signal    
);

logic w_p_signal;

always_ff @( posedge i_clk or negedge i_rst_n ) begin : proc_detect_edge
    if(~i_rst_n) begin
        w_p_signal <= 1'b0;
        o_signal   <= 1'b0;
    end else begin
        w_p_signal <= i_signal;
        if(i_pos_edge) 
            o_signal <= (i_signal & (~w_p_signal));
        else
            o_signal <= (~i_signal & (w_p_signal));
            
    end
end


endmodule

03_verif/Test-Sub_module/TB_SS_detect_edge/tb_SS_detect_edge.sv
`timescale 1ns/1ps
module tb_SS_detect_edge();

logic i_clk, i_rst_n, i_pos_edge;
logic i_signal, o_signal;

// i_pos_edge = 0 -> detect negedge edge
// i_pos_edge = 1 -> detect posedge edge
SS_detect_edge DUT (
    .i_clk       (i_clk),
    .i_rst_n     (i_rst_n),
    .i_pos_edge  (i_pos_edge),
    .i_signal    (i_signal),
    .o_signal    (o_signal)
);

initial begin
    $dumpfile("./tb_SS_detect_edge.vcd");
    $dumpvars(0, tb_SS_detect_edge);
end

initial begin
    i_clk = 1'b0;
    forever begin
        #10 i_clk = ~i_clk;
    end 
end 

initial begin
    i_rst_n = 1'b0;
    #30;
    i_rst_n = 1'b1;
    #10;
    i_pos_edge = 1'b1;
    i_signal = 1'b0;
    #20;
    i_signal = 1'b1;
    #40;
    @(posedge i_clk);
    i_signal = 1'b1;
    @(posedge i_clk);
    i_signal = 1'b0;

    #10;
    i_pos_edge = 1'b1;
    i_signal = 1'b0;
    #20;
    i_signal = 1'b1;
    #10;
    i_signal = 1'b0;
    #20;
    @(posedge i_clk);
    i_signal = 1'b1;
    @(posedge i_clk);
    i_signal = 1'b0;

    #100;
    $finish;
end 

endmodule

03_verif/Test-Sub_module/TB_SS_detect_edge/tb_SS_detect_edge.vcd
$version Generated by VerilatedVcd $end
$timescale 1ps $end
 $scope module TOP $end
  $scope module tb_SS_detect_edge $end
   $var wire 1 # i_clk $end
   $var wire 1 $ i_rst_n $end
   $var wire 1 % i_pos_edge $end
   $var wire 1 & i_signal $end
   $var wire 1 ' o_signal $end
   $scope module DUT $end
    $var wire 1 # i_clk $end
    $var wire 1 $ i_rst_n $end
    $var wire 1 % i_pos_edge $end
    $var wire 1 & i_signal $end
    $var wire 1 ' o_signal $end
    $var wire 1 ( w_p_signal $end
   $upscope $end
  $upscope $end
 $upscope $end
$enddefinitions $end


#0
0#
0$
0%
0&
0'
0(
#10000
1#
#20000
0#
#30000
1#
1$
#40000
0#
1%
#50000
1#
#60000
0#
1&
#70000
1#
1'
1(
#80000
0#
#90000
1#
0'
#100000
0#
#110000
1#
#120000
0#
#130000
1#
0&
0(
#140000
0#
#150000
1#
#160000
0#
1&
#170000
1#
0&
#180000
0#
#190000
1#
#200000
0#
#210000
1#
1&
1'
1(
#220000
0#
#230000
1#
0&
0'
0(
