02_rtl/SS_detect_start.sv
// if i_start is high while i_done is high, w_start is held low.
// once i_done goes low, w_start follows i_start on the next clock edge
module SS_detect_start(
    input logic                         i_clk       ,
    input logic                         i_rst_n     ,
    input logic                         i_start     ,
    input logic                         i_done      ,
    output logic                        o_w_start   
);

logic w_next_start;
assign o_w_start = (i_done) ? 1'b0 : w_next_start;

always_ff @( posedge i_clk or negedge i_rst_n ) begin
    if(~i_rst_n)
        w_next_start <= 1'b0;
    else
        w_next_start <= ((~o_w_start) & (i_start)) ? (~o_w_start) : (o_w_start);
end

endmodule

03_verif/Test-Sub_module/TB_SS_detect_start/tb_SS_detect_start.sv
`timescale 1ns/1ps

module tb_SS_detect_start;

logic                         i_clk;
logic                         i_rst_n;
logic                         i_start;
logic                         i_done;
logic                         o_w_start;

SS_detect_start DUT (
    .i_clk       (i_clk),
    .i_rst_n     (i_rst_n),
    .i_start     (i_start),
    .i_done      (i_done),
    .o_w_start   (o_w_start)
);

initial begin
    i_clk = 1'b0;
    forever begin
        #10 i_clk = ~i_clk;
    end
end

initial begin
    $dumpfile("./tb_SS_detect_start.vcd");
    $dumpvars(0, tb_SS_detect_start);
end

initial begin
    i_rst_n = 1'b0;

    #30;

    i_rst_n = 1'b1;

    #10;

    @(posedge i_clk);
    i_start = 1'b1;
    i_done  = 1'b1;
    @(posedge i_clk);
    i_start = 1'b1;
    i_done  = 1'b0;

    #40;

    @(posedge i_clk);
    i_start = 0;
    i_done = 1;
    @(posedge i_clk);
    i_start = 1;
    i_done = 0;

    #40;

    @(posedge i_clk);
    i_start = 1;
    i_done = 1;

    #40;

    @(posedge i_clk);
    i_done = 0;

    @(posedge i_clk);
    i_start = 0;

    #40;

    @(posedge i_clk);
    i_done = 1;

    @(posedge i_clk);
    i_done = 0;
    @(posedge i_clk);
    i_start = 1;
    #100;
    $finish;
end

endmodule

03_verif/Test-Sub_module/TB_SS_detect_start/tb_SS_detect_start.vcd
$version Generated by VerilatedVcd $end
$timescale 1ps $end
 $scope module TOP $end
  $scope module tb_SS_detect_start $end
   $var wire 1 # i_clk $end
   $var wire 1 $ i_rst_n $end
   $var wire 1 % i_start $end
   $var wire 1 & i_done $end
   $var wire 1 ' o_w_start $end
   $scope module DUT $end
    $var wire 1 # i_clk $end
    $var wire 1 $ i_rst_n $end
    $var wire 1 % i_start $end
    $var wire 1 & i_done $end
    $var wire 1 ' o_w_start $end
    $var wire 1 ( w_next_start $end
   $upscope $end
  $upscope $end
 $upscope $end
$enddefinitions $end


#0
0#
0$
0%
0&
0'
0(
#10000
1#
#20000
0#
#30000
1#
1$
#40000
0#
#50000
1#
1%
1&
1(
#60000
0#
#70000
1#
0&
1'
#80000
0#
#90000
1#
#100000
0#
#110000
1#
#120000
0#
#130000
1#
0%
1&
0'
0(
#140000
0#
#150000
1#
1%
0&
1'
1(
#160000
0#
#170000
1#
#180000
0#
#190000
1#
#200000
0#
#210000
1#
1&
0'
#220000
0#
#230000
1#
#240000
0#
#250000
1#
#260000
0#
#270000
1#
0&
1'
#280000
0#
#290000
1#
0%
#300000
0#
#310000
1#
#320000
0#
#330000
1#
#340000
0#
#350000
1#
1&
0'
0(
#360000
0#
#370000
1#
0&
#380000
0#
#390000
1#
1%
1'
1(
