02_rtl/SS_detect_edge.sv
// i_pos_edge = 0 -> detect negedge edge
// i_pos_edge = 1 -> detect posedge edge
module SS_detect_edge(
    input logic                 i_clk       ,
    input logic                 i_rst_n     ,
    input logic                 i_pos_edge  ,
    input logic                 i_signal    ,
    output logic                o_signal    
);

logic w_p_signal;

always_ff @( posedge i_clk or negedge i_rst_n ) begin : proc_detect_edge
    if(~i_rst_n) begin
        w_p_signal <= 1'b0;
        o_signal   <= 1'b0;
    end else begin
        w_p_signal <= i_signal;
        if(i_pos_edge) 
            o_signal <= (i_signal & (~w_p_signal));
        else
            o_signal <= (~i_signal & (w_p_signal));
            
    end
end


endmodule

02_rtl/SS_write_data.sv
module SS_write_data #(
    parameter SIZE_ADDR = 6 ,
    parameter SIZE_DATA = 8
)(
    input logic                     i_clk               ,
    input logic                     i_rst_n             ,
    
    input logic                     i_start_write_data   ,
    input logic                     i_en_write_data      ,

    input logic [SIZE_ADDR-1:0]     i_si_ram            ,
    input logic [SIZE_ADDR-1:0]     i_ei_ram            ,

    input logic [SIZE_DATA-1:0]     i_data_ram          ,

    output logic                    o_we_ram            ,
    output logic [SIZE_ADDR-1:0]    o_addr_ram          ,
    output logic [SIZE_DATA-1:0]    o_data_ram          ,

    output logic                    o_done_write_data    
);

// processing the signal detecting i_start_write_data
logic w_update_start;
SS_detect_edge detect_edge_unit(
    .i_clk       (i_clk),
    .i_rst_n     (i_rst_n),
    .i_pos_edge  (1'b1),
    .i_signal    (i_start_write_data),
    .o_signal    (w_update_start)
);

// processing the signal detecting i_en_write_data
logic w_update_en;
logic w_update_en_start;
always_ff @( posedge i_clk or negedge i_rst_n ) begin : proc_update_en_start
    if(~i_rst_n) begin
        w_update_en_start <= 1'b0; 
    end else begin
        w_update_en_start <= (w_update_start) ? 1'b1 : ((o_done_write_data) ? 1'b0 : w_update_en_start); 
    end
end
assign w_update_en = i_en_write_data & (w_update_en_start);

// processing the compare of i_ei_ram and o_addr_ram
logic w_compare_ei;
assign w_compare_ei = (i_ei_ram == o_addr_ram) & w_update_en_start;
always_ff @( posedge i_clk or negedge i_rst_n ) begin
    if(~i_rst_n) begin
        o_done_write_data  <= '0; 
    end else begin
        o_done_write_data  <= w_compare_ei; 
    end
end

// processing o_addr_ram
logic [SIZE_ADDR-1:0] w_next_addr_ram;
assign w_next_addr_ram = o_addr_ram + 1'b1;
always_ff @( posedge i_clk or negedge i_rst_n ) begin : proc_o_addr_ram
    if(~i_rst_n) begin
        o_addr_ram  <= '0; 
    end else begin
        o_addr_ram  <= (w_update_start) ? i_si_ram : ((w_update_en) ? w_next_addr_ram :  o_addr_ram); 
    end
end

// processing o_data_ram and 0_data_valid
always_ff @( posedge i_clk or negedge i_rst_n ) begin
    if(~i_rst_n) 
        o_data_ram   <= '0;
    else
        o_data_ram    <= i_data_ram;
end
always_ff @( posedge i_clk or negedge i_rst_n ) begin
    if(~i_rst_n) 
        o_we_ram   <= '0;
    else
        o_we_ram    <= (w_update_en & (~o_done_write_data));
end


endmodule

03_verif/Test-Sub_module/TB_SS_write_data/tb_SS_write_data.sv
`timescale 1ns/1ps

module tb_SS_write_data;

    // Parameter
    localparam SIZE_ADDR = 6;
    localparam SIZE_DATA = 8;

    // Signals
    logic                     i_clk;
    logic                     i_rst_n;

    logic                     i_start_write_data;
    logic                     i_en_write_data;

    logic [SIZE_ADDR-1:0]     i_si_ram;
    logic [SIZE_ADDR-1:0]     i_ei_ram;

    logic [SIZE_DATA-1:0]     i_data_ram;

    logic                     o_we_ram;
    logic [SIZE_ADDR-1:0]     o_addr_ram;
    logic [SIZE_DATA-1:0]     o_data_ram;

    logic                     o_done_write_data;

    // Clock generation (10ns period)
    initial i_clk = 0;
    always #5 i_clk = ~i_clk;

    // DUT instantiation
    SS_write_data #(
        .SIZE_ADDR(SIZE_ADDR),
        .SIZE_DATA(SIZE_DATA)
    ) dut (
        .i_clk(i_clk),
        .i_rst_n(i_rst_n),
        .i_start_write_data(i_start_write_data),
        .i_en_write_data(i_en_write_data),
        .i_si_ram(i_si_ram),
        .i_ei_ram(i_ei_ram),
        .i_data_ram(i_data_ram),
        .o_we_ram(o_we_ram),
        .o_addr_ram(o_addr_ram),
        .o_data_ram(o_data_ram),
        .o_done_write_data(o_done_write_data)
    );

    initial begin
        $dumpfile("./tb_SS_write_data.vcd");
        $dumpvars(0, tb_SS_write_data);
    end

    // Testbench process
    initial begin
        i_rst_n = 1'b0;
        i_start_write_data = 1'b0;
        i_en_write_data = 1'b0;
        i_si_ram = 0;
        i_ei_ram = 0;
        i_data_ram = 0;

        #30;
        i_rst_n = 1'b1;

        #10;
        // --- Test 1: Ghi từ 5 -> 10 ---
        @(posedge i_clk);
        i_si_ram = 6'd5;
        i_ei_ram = 6'd10;
        i_start_write_data = 1'b1;
        @(posedge i_clk);
        i_start_write_data = 1'b0;

        i_en_write_data = 1'b1;

        // Ghi dữ liệu liên tiếp
        forever begin
            @(posedge i_clk);
            i_data_ram = {2'b00, o_addr_ram}; // Data = Addr
            if (o_done_write_data) break;
        end

        @(posedge i_clk);
        i_en_write_data = 1'b0;

        // --- Test 2: Ghi từ 0 -> 3 ---
        repeat (5) @(posedge i_clk);
        i_si_ram = 6'd0;
        i_ei_ram = 6'd3;
        i_start_write_data = 1'b1;
        @(posedge i_clk);
        i_start_write_data = 1'b0;
        i_en_write_data = 1'b1;

        forever begin
            @(posedge i_clk);
            i_data_ram = {2'b11, o_addr_ram}; // Data = Addr + pattern
            if (o_done_write_data) break;
        end

        @(posedge i_clk);
        i_en_write_data = 1'b0;

        // --- Test 3: Ngắt giữa chừng ---
        repeat (5) @(posedge i_clk);
        i_si_ram = 6'd8;
        i_ei_ram = 6'd12;
        i_start_write_data = 1'b1;
        @(posedge i_clk);
        i_start_write_data = 1'b0;
        i_en_write_data = 1'b1;

        // Ghi được 2 giá trị thì tắt enable
        repeat (2) @(posedge i_clk);
        i_data_ram = 8'hAA;
        i_en_write_data = 1'b0;

        // Đợi vài chu kỳ rồi bật lại enable
        repeat (3) @(posedge i_clk);
        i_en_write_data = 1'b1;

        forever begin
            @(posedge i_clk);
            i_data_ram = 8'hBB;
            if (o_done_write_data) break;
        end

        @(posedge i_clk);
        i_en_write_data = 1'b0;

        repeat (5) @(posedge i_clk);
        $finish;
    end

endmodule

03_verif/Test-Sub_module/TB_SS_write_data/tb_SS_write_data.vcd
$version Generated by VerilatedVcd $end
$timescale 1ps $end
 $scope module TOP $end
  $scope module tb_SS_write_data $end
   $var wire 32 4 SIZE_ADDR [31:0] $end
   $var wire 32 5 SIZE_DATA [31:0] $end
   $var wire 1 1 i_clk $end
   $var wire 1 # i_rst_n $end
   $var wire 1 $ i_start_write_data $end
   $var wire 1 % i_en_write_data $end
   $var wire 6 & i_si_ram [5:0] $end
   $var wire 6 ' i_ei_ram [5:0] $end
   $var wire 8 ( i_data_ram [7:0] $end
   $var wire 1 ) o_we_ram $end
   $var wire 6 * o_addr_ram [5:0] $end
   $var wire 8 + o_data_ram [7:0] $end
   $var wire 1 , o_done_write_data $end
   $scope module dut $end
    $var wire 32 4 SIZE_ADDR [31:0] $end
    $var wire 32 5 SIZE_DATA [31:0] $end
    $var wire 1 1 i_clk $end
    $var wire 1 # i_rst_n $end
    $var wire 1 $ i_start_write_data $end
    $var wire 1 % i_en_write_data $end
    $var wire 6 & i_si_ram [5:0] $end
    $var wire 6 ' i_ei_ram [5:0] $end
    $var wire 8 ( i_data_ram [7:0] $end
    $var wire 1 ) o_we_ram $end
    $var wire 6 * o_addr_ram [5:0] $end
    $var wire 8 + o_data_ram [7:0] $end
    $var wire 1 , o_done_write_data $end
    $var wire 1 - w_update_start $end
    $var wire 1 2 w_update_en $end
    $var wire 1 . w_update_en_start $end
    $var wire 1 3 w_compare_ei $end
    $var wire 6 / w_next_addr_ram [5:0] $end
    $scope module detect_edge_unit $end
     $var wire 1 1 i_clk $end
     $var wire 1 # i_rst_n $end
     $var wire 1 6 i_pos_edge $end
     $var wire 1 $ i_signal $end
     $var wire 1 - o_signal $end
     $var wire 1 0 w_p_signal $end
    $upscope $end
   $upscope $end
  $upscope $end
 $upscope $end
$enddefinitions $end


#0
0#
0$
0%
b000000 &
b000000 '
b00000000 (
0)
b000000 *
b00000000 +
0,
0-
0.
b000001 /
00
01
02
03
b00000000000000000000000000000110 4
b00000000000000000000000000001000 5
16
#5000
11
#10000
01
#15000
11
#20000
01
#25000
11
#30000
1#
01
#35000
11
#40000
01
#45000
1$
b000101 &
b001010 '
1-
10
11
#50000
01
#55000
0$
1%
b000101 *
0-
1.
b000110 /
00
11
12
#60000
01
#65000
b00000101 (
1)
b000110 *
b00000101 +
b000111 /
11
#70000
01
#75000
b00000110 (
b000111 *
b00000110 +
b001000 /
11
#80000
01
#85000
b00000111 (
b001000 *
b00000111 +
b001001 /
11
#90000
01
#95000
b00001000 (
b001001 *
b00001000 +
b001010 /
11
#100000
01
#105000
b00001001 (
b001010 *
b00001001 +
b001011 /
11
13
#110000
01
#115000
b00001010 (
b001011 *
b00001010 +
1,
b001100 /
11
03
#120000
01
#125000
b00001011 (
0)
b001100 *
b00001011 +
0,
0.
b001101 /
11
02
#130000
01
#135000
0%
11
#140000
01
#145000
11
#150000
01
#155000
11
#160000
01
#165000
11
#170000
01
#175000
11
#180000
01
#185000
1$
b000000 &
b000011 '
1-
10
11
#190000
01
#195000
0$
1%
b000000 *
0-
1.
b000001 /
00
11
12
#200000
01
#205000
b11000000 (
1)
b000001 *
b11000000 +
b000010 /
11
#210000
01
#215000
b11000001 (
b000010 *
b11000001 +
b000011 /
11
#220000
01
#225000
b11000010 (
b000011 *
b11000010 +
b000100 /
11
13
#230000
01
#235000
b11000011 (
b000100 *
b11000011 +
1,
b000101 /
11
03
#240000
01
#245000
b11000100 (
0)
b000101 *
b11000100 +
0,
0.
b000110 /
11
02
#250000
01
#255000
0%
11
#260000
01
#265000
11
#270000
01
#275000
11
#280000
01
#285000
11
#290000
01
#295000
11
#300000
01
#305000
1$
b001000 &
b001100 '
1-
10
11
#310000
01
#315000
0$
1%
b001000 *
0-
1.
b001001 /
00
11
12
#320000
01
#325000
1)
b001001 *
b001010 /
11
#330000
01
#335000
0%
b10101010 (
0)
b10101010 +
11
02
#340000
01
#345000
11
#350000
01
#355000
11
#360000
01
#365000
1%
1)
b001010 *
b001011 /
11
12
#370000
01
#375000
b10111011 (
b001011 *
b10111011 +
b001100 /
11
#380000
01
#385000
b001100 *
b001101 /
11
13
#390000
01
#395000
b001101 *
1,
b001110 /
11
03
#400000
01
#405000
0)
b001110 *
0,
0.
b001111 /
11
02
#410000
01
#415000
0%
11
