02_rtl/SS_detect_edge.sv
// i_pos_edge = 0 -> detect negedge edge
// i_pos_edge = 1 -> detect posedge edge
module SS_detect_edge(
    input logic                 i_clk       ,
    input logic                 i_rst_n     ,
    input logic                 i_pos_edge  ,
    input logic                 i_signal    ,
    output logic                o_signal    
);

logic w_p_signal;

always_ff @( posedge i_clk or negedge i_rst_n ) begin : proc_detect_edge
    if(~i_rst_n) begin
        w_p_signal <= 1'b0;
        o_signal   <= 1'b0;
    end else begin
        w_p_signal <= i_signal;
        if(i_pos_edge) 
            o_signal <= (i_signal & (~w_p_signal));
        else
            o_signal <= (~i_signal & (w_p_signal));
            
    end
end


endmodule

02_rtl/SS_read_data.sv
module SS_read_data #(
    parameter SIZE_ADDR = 6 ,
    parameter SIZE_DATA = 8
)(
    input logic                     i_clk               ,
    input logic                     i_rst_n             ,
    input logic                     i_start_read_data   ,
    input logic                     i_en_read_data      ,

    input logic [SIZE_ADDR-1:0]     i_si_ram            ,
    input logic [SIZE_ADDR-1:0]     i_ei_ram            ,

    input logic [SIZE_DATA-1:0]     i_data_ram          ,
    output logic [SIZE_ADDR-1:0]    o_addr_ram          ,
    output logic [SIZE_DATA-1:0]    o_data_ram          ,

    output logic                    o_data_valid        ,
    output logic                    o_done_read_data    
);

// processing the signal detecting i_start_read_data
logic w_update_start;
SS_detect_edge detect_edge_unit(
    .i_clk       (i_clk),
    .i_rst_n     (i_rst_n),
    .i_pos_edge  (1'b1),
    .i_signal    (i_start_read_data),
    .o_signal    (w_update_start)
);

// processing the signal detecting i_en_read_data
logic w_update_en;
logic w_update_en_start, w_update_en_start_next;
logic w_update_en_done;
always_ff @( posedge i_clk or negedge i_rst_n ) begin : proc_update_en_start
    if(~i_rst_n) begin
        w_update_en_start_next <= 1'b0; 
    end else begin
        w_update_en_start_next <= (w_update_en_done) ? 1'b0 : w_update_en_start; 
    end
end
assign w_update_en_start = (w_update_start) ? 1'b1 : w_update_en_start_next;
assign w_update_en = i_en_read_data & (w_update_en_start);

// processing the compare of i_ei_ram and o_addr_ram
logic w_compare_ei;
assign w_compare_ei = (i_ei_ram == o_addr_ram);
always_ff @( posedge i_clk or negedge i_rst_n ) begin
    if(~i_rst_n) begin
        w_update_en_done  <= '0; 
    end else begin
        w_update_en_done  <= w_compare_ei; 
    end
end

// processing o_addr_ram
logic [SIZE_ADDR-1:0] w_next_addr_ram;
assign w_next_addr_ram = o_addr_ram + 1'b1;
always_ff @( posedge i_clk or negedge i_rst_n ) begin : proc_o_addr_ram
    if(~i_rst_n) begin
        o_addr_ram  <= '0; 
    end else begin
        o_addr_ram  <= (w_update_start) ? i_si_ram : ((w_update_en) ? w_next_addr_ram :  o_addr_ram); 
    end
end

// processing o_data_ram and 0_data_valid
always_ff @( posedge i_clk or negedge i_rst_n ) begin : proc_o_data_valid
    if(~i_rst_n)
        o_data_valid    <= 1'b0;
    else
        o_data_valid    <= w_update_en;
end
assign o_data_ram = (o_data_valid) ? i_data_ram : '0;

// processing o_done_read_data
always_ff @( posedge i_clk or negedge i_rst_n ) begin : proc_o_done
    if(~i_rst_n) 
        o_done_read_data <= 1'b0;
    else
        o_done_read_data <= w_update_en_done;
end

endmodule

03_verif/Test-Sub_module/MODULE_TB/tb_simple_dual_port_ram_single_clock.sv
module tb_simple_dual_port_ram_single_clock#(
    parameter DATA_WIDTH = 8,
    parameter ADDR_WIDTH = 6,
    parameter MEM_INIT_FILE = "./mem_init.hex"
)(
    input  logic                     clk,
    input  logic                     rst_n,
    input  logic                     we,
    input  logic [DATA_WIDTH-1:0]    data,
    input  logic [ADDR_WIDTH-1:0]    read_addr,
    input  logic [ADDR_WIDTH-1:0]    write_addr,
    output logic [DATA_WIDTH-1:0]    q
);


    logic [DATA_WIDTH-1:0] ram [0:(2**ADDR_WIDTH)-1];

    initial begin
        if (MEM_INIT_FILE != "") begin
            $display("Loading memory contents from %s", MEM_INIT_FILE);
            $readmemh(MEM_INIT_FILE, ram);
        end
    end

    always_ff @(negedge rst_n) begin
        if (!rst_n && MEM_INIT_FILE != "") begin
            $readmemh(MEM_INIT_FILE, ram);
        end
    end

    always_ff @(posedge clk) begin
        q <= ram[read_addr];
        if (we)
            ram[write_addr] <= data;
    end

endmodule

03_verif/Test-Sub_module/TB_SS_read_data/tb_SS_read_data.sv
`timescale 1ns/1ps

module tb_SS_read_data();

    parameter SIZE_ADDR = 6;
    parameter SIZE_DATA = 8;
    parameter MEM_INIT_FILE = "./../MODULE_TB/mem_init.hex";
    logic                     i_clk;
    logic                     i_rst_n;
    logic                     i_start_read_data;
    logic                     i_en_read_data;

    logic [SIZE_ADDR-1:0]     i_si_ram;
    logic [SIZE_ADDR-1:0]     i_ei_ram;

    logic [SIZE_DATA-1:0]     i_data_ram;
    logic [SIZE_ADDR-1:0]     o_addr_ram;
    logic [SIZE_DATA-1:0]     o_data_ram;

    logic                     o_data_valid;
    logic                     o_done_read_data;   

    tb_simple_dual_port_ram_single_clock #(
        .DATA_WIDTH (SIZE_DATA),
        .ADDR_WIDTH (SIZE_ADDR),
        .MEM_INIT_FILE(MEM_INIT_FILE)
    ) BRAM_UNIT (
        .clk        (i_clk),
        .rst_n      (i_rst_n),
        .we         (1'b0),
        .data       (),
        .read_addr  (o_addr_ram),
        .write_addr (),
        .q          (i_data_ram)
    );

    SS_read_data #(
        .SIZE_ADDR (SIZE_ADDR),
        .SIZE_DATA (SIZE_DATA)
    ) DUT (
        .i_clk               (i_clk),
        .i_rst_n             (i_rst_n),
        .i_start_read_data   (i_start_read_data),
        .i_en_read_data      (i_en_read_data),

        .i_si_ram            (i_si_ram),
        .i_ei_ram            (i_ei_ram),
        .i_data_ram          (i_data_ram),
        .o_addr_ram          (o_addr_ram),
        .o_data_ram          (o_data_ram),
        .o_data_valid        (o_data_valid),
        .o_done_read_data    (o_done_read_data)
    );

    initial begin
        $dumpfile("./tb_SS_read_data.vcd");
        $dumpvars(0, tb_SS_read_data);
    end

    // Clock 20ns
    initial begin
        i_clk = 1'b0;
        forever #10 i_clk = ~i_clk;
    end

    // Test sequence
    initial begin
        // Init
        i_rst_n = 1'b0;
        i_start_read_data = 1'b0;
        i_en_read_data = 1'b0;
        i_si_ram = 0;
        i_ei_ram = 0;

        // Reset
        repeat (3) @(posedge i_clk);
        i_rst_n = 1'b1;

        // --- Test 1: Đọc từ 5 -> 10 ---
        @(posedge i_clk);
        i_si_ram = 6'd5;
        i_ei_ram = 6'd10;
        i_start_read_data = 1'b1;  // Kích start
        @(posedge i_clk);
        i_start_read_data = 1'b0;  // Thả start

        // Bật enable để đọc
        i_en_read_data = 1'b1;

        // Chờ done
        wait (o_done_read_data);
        @(posedge i_clk);
        i_en_read_data = 1'b0;

        // --- Test 2: Đọc lại từ 0 -> 3 ---
        repeat (5) @(posedge i_clk);
        i_si_ram = 6'd0;
        i_ei_ram = 6'd3;
        i_start_read_data = 1'b1;
        @(posedge i_clk);
        i_start_read_data = 1'b0;
        i_en_read_data = 1'b1;

        wait (o_done_read_data);
        @(posedge i_clk);
        i_en_read_data = 1'b0;

        // --- Test 3: Ngắt giữa chừng ---
        repeat (5) @(posedge i_clk);
        i_si_ram = 6'd8;
        i_ei_ram = 6'd12;
        i_start_read_data = 1'b1;
        @(posedge i_clk);
        i_start_read_data = 1'b0;
        i_en_read_data = 1'b1;

        // Đọc được 2 giá trị thì tắt enable
        repeat (2) @(posedge i_clk);
        i_en_read_data = 1'b0;

        // Đợi vài chu kỳ rồi bật lại enable
        repeat (3) @(posedge i_clk);
        i_en_read_data = 1'b1;

        wait (o_done_read_data);
        @(posedge i_clk);
        i_en_read_data = 1'b0;

        // Kết thúc mô phỏng
        repeat (5) @(posedge i_clk);
        $finish;
    end

endmodule

03_verif/Test-Sub_module/TB_SS_read_data/tb_SS_read_data.vcd
$version Generated by VerilatedVcd $end
$timescale 1ps $end
 $scope module TOP $end
  $scope module tb_SS_read_data $end
   $var wire 32 6 SIZE_ADDR [31:0] $end
   $var wire 32 7 SIZE_DATA [31:0] $end
   $var wire 216 8 MEM_INIT_FILE [215:0] $end
   $var wire 1 / i_clk $end
   $var wire 1 # i_rst_n $end
   $var wire 1 $ i_start_read_data $end
   $var wire 1 % i_en_read_data $end
   $var wire 6 & i_si_ram [5:0] $end
   $var wire 6 ' i_ei_ram [5:0] $end
   $var wire 8 0 i_data_ram [7:0] $end
   $var wire 6 1 o_addr_ram [5:0] $end
   $var wire 8 2 o_data_ram [7:0] $end
   $var wire 1 ( o_data_valid $end
   $var wire 1 ) o_done_read_data $end
   $scope module BRAM_UNIT $end
    $var wire 32 7 DATA_WIDTH [31:0] $end
    $var wire 32 6 ADDR_WIDTH [31:0] $end
    $var wire 216 8 MEM_INIT_FILE [215:0] $end
    $var wire 1 / clk $end
    $var wire 1 # rst_n $end
    $var wire 1 ? we $end
    $var wire 8 @ data [7:0] $end
    $var wire 6 1 read_addr [5:0] $end
    $var wire 6 A write_addr [5:0] $end
    $var wire 8 0 q [7:0] $end
   $upscope $end
   $scope module DUT $end
    $var wire 32 6 SIZE_ADDR [31:0] $end
    $var wire 32 7 SIZE_DATA [31:0] $end
    $var wire 1 / i_clk $end
    $var wire 1 # i_rst_n $end
    $var wire 1 $ i_start_read_data $end
    $var wire 1 % i_en_read_data $end
    $var wire 6 & i_si_ram [5:0] $end
    $var wire 6 ' i_ei_ram [5:0] $end
    $var wire 8 0 i_data_ram [7:0] $end
    $var wire 6 1 o_addr_ram [5:0] $end
    $var wire 8 2 o_data_ram [7:0] $end
    $var wire 1 ( o_data_valid $end
    $var wire 1 ) o_done_read_data $end
    $var wire 1 * w_update_start $end
    $var wire 1 3 w_update_en $end
    $var wire 1 + w_update_en_start $end
    $var wire 1 , w_update_en_start_next $end
    $var wire 1 - w_update_en_done $end
    $var wire 1 4 w_compare_ei $end
    $var wire 6 5 w_next_addr_ram [5:0] $end
    $scope module detect_edge_unit $end
     $var wire 1 / i_clk $end
     $var wire 1 # i_rst_n $end
     $var wire 1 B i_pos_edge $end
     $var wire 1 $ i_signal $end
     $var wire 1 * o_signal $end
     $var wire 1 . w_p_signal $end
    $upscope $end
   $upscope $end
  $upscope $end
 $upscope $end
$enddefinitions $end


#0
0#
0$
0%
b000000 &
b000000 '
0(
0)
0*
0+
0,
0-
0.
0/
b00000000 0
b000000 1
b00000000 2
03
14
b000001 5
b00000000000000000000000000000110 6
b00000000000000000000000000001000 7
b001011100010111100101110001011100010111101001101010011110100010001010101010011000100010101011111010101000100001000101111011011010110010101101101010111110110100101101110011010010111010000101110011010000110010101111000 8
0?
b00000000 @
b000000 A
1B
#10000
1/
#20000
0/
#30000
1/
#40000
0/
#50000
1#
1-
1/
#60000
0/
#70000
1$
b000101 &
b001010 '
1)
1*
1+
0-
1.
1/
04
#80000
0/
#90000
0$
1%
1(
0)
0*
1,
0.
1/
b000101 1
13
b000110 5
#100000
0/
#110000
0%
0(
1/
03
#120000
0/
#130000
1/
#140000
0/
#150000
1/
#160000
0/
#170000
1/
#180000
0/
#190000
1/
#200000
0/
#210000
1$
b000000 &
b000011 '
1*
1.
1/
#220000
0/
#230000
0$
1%
1(
0*
0.
1/
b000000 1
13
b000001 5
#240000
0/
#250000
1/
b000001 1
b000010 5
#260000
0/
#270000
1/
b000010 1
b000011 5
#280000
0/
#290000
1/
b000011 1
14
b000100 5
#300000
0/
#310000
1-
1/
b000100 1
04
b000101 5
#320000
0/
#330000
1)
0+
0,
0-
1/
b000101 1
03
b000110 5
#340000
0/
#350000
0%
0(
0)
1/
#360000
0/
#370000
1/
#380000
0/
#390000
1/
#400000
0/
#410000
1/
#420000
0/
#430000
1/
#440000
0/
#450000
1$
b001000 &
b001100 '
1*
1+
1.
1/
#460000
0/
#470000
0$
1%
1(
0*
1,
0.
1/
b001000 1
13
b001001 5
#480000
0/
#490000
1/
b001001 1
b001010 5
#500000
0/
#510000
0%
0(
1/
03
#520000
0/
#530000
1/
#540000
0/
#550000
1/
#560000
0/
#570000
1%
1(
1/
b001010 1
13
b001011 5
#580000
0/
#590000
1/
b001011 1
b001100 5
#600000
0/
#610000
1/
b001100 1
14
b001101 5
#620000
0/
#630000
1-
1/
b001101 1
04
b001110 5
#640000
0/
#650000
1)
0+
0,
0-
1/
b001110 1
03
b001111 5
#660000
0/
#670000
0%
0(
0)
1/
